colemen_object_utils.py
utils/dict.py
colemen_object_utils-1.0.0.dist-info/METADATA
colemen_object_utils-1.0.0.dist-info/WHEEL
colemen_object_utils-1.0.0.dist-info/top_level.txt
colemen_object_utils-1.0.0.dist-info/RECORD
